[
  {
    "id": 1,
    "sido": "서울",
    "name": "서울가락동농수산물도매시장",
    "category": "공영",
    "opened": "198506",
    "corp_count": 9,
    "merchant_count": 0,
    "land_area_sqm": 543451,
    "geocode_query": "서울 송파구 가락동 가락시장",
    "lat": 37.4931855,
    "lng": 127.1181478,
    "geocode_source": "landmark"
  },
  {
    "id": 2,
    "sido": "서울",
    "name": "서울강서농산물도매시장",
    "category": "공영",
    "opened": "200402",
    "corp_count": 3,
    "merchant_count": 60,
    "land_area_sqm": 213032,
    "geocode_query": "서울 강서구 외발산동 농산물도매시장",
    "lat": 37.5476771,
    "lng": 126.818987,
    "geocode_source": "district"
  },
  {
    "id": 3,
    "sido": "부산",
    "name": "부산엄궁농산물도매시장",
    "category": "공영",
    "opened": "199312",
    "corp_count": 3,
    "merchant_count": 0,
    "land_area_sqm": 154190,
    "geocode_query": "부산 사상구 엄궁동 농산물도매시장",
    "lat": 35.1253561,
    "lng": 128.9725345,
    "geocode_source": "district"
  },
  {
    "id": 4,
    "sido": "부산",
    "name": "부산반여농산물도매시장",
    "category": "공영",
    "opened": "200012",
    "corp_count": 3,
    "merchant_count": 0,
    "land_area_sqm": 151642,
    "geocode_query": "부산 해운대구 반여동 농산물도매시장",
    "lat": 35.204244,
    "lng": 129.1318139,
    "geocode_source": "district"
  },
  {
    "id": 5,
    "sido": "부산",
    "name": "부산국제수산물도매시장",
    "category": "공영",
    "opened": "200809",
    "corp_count": 4,
    "merchant_count": 0,
    "land_area_sqm": 102011,
    "geocode_query": "부산 서구 암남동 국제수산물도매시장",
    "lat": 35.0751352,
    "lng": 129.0152617,
    "geocode_source": "district"
  },
  {
    "id": 6,
    "sido": "대구",
    "name": "대구북부농수산물도매시장",
    "category": "공영",
    "opened": "198810",
    "corp_count": 5,
    "merchant_count": 8,
    "land_area_sqm": 196824,
    "geocode_query": "대구 북구 매천동 농수산물도매시장",
    "lat": 35.913,
    "lng": 128.53976,
    "geocode_source": "district"
  },
  {
    "id": 7,
    "sido": "인천",
    "name": "인천남촌농산물도매시장",
    "category": "공영",
    "opened": "199401",
    "corp_count": 4,
    "merchant_count": 0,
    "land_area_sqm": 196851,
    "geocode_query": "인천 남동구 남촌동 농산물도매시장",
    "lat": 37.427366,
    "lng": 126.7120811,
    "geocode_source": "district"
  },
  {
    "id": 8,
    "sido": "인천",
    "name": "인천삼산농산물도매시장",
    "category": "공영",
    "opened": "200105",
    "corp_count": 3,
    "merchant_count": 0,
    "land_area_sqm": 107912,
    "geocode_query": "인천 부평구 삼산동 농산물도매시장",
    "lat": 37.5151336,
    "lng": 126.7418482,
    "geocode_source": "district"
  },
  {
    "id": 9,
    "sido": "광주",
    "name": "광주각화동농산물도매시장",
    "category": "공영",
    "opened": "199102",
    "corp_count": 3,
    "merchant_count": 0,
    "land_area_sqm": 56206,
    "geocode_query": "광주 북구 각화동 농산물도매시장",
    "lat": 35.1848428,
    "lng": 126.9398536,
    "geocode_source": "district"
  },
  {
    "id": 10,
    "sido": "광주",
    "name": "광주서부농수산물도매시장",
    "category": "공영",
    "opened": "200404",
    "corp_count": 4,
    "merchant_count": 0,
    "land_area_sqm": 111201,
    "geocode_query": "광주 서구 매월동 농수산물도매시장",
    "lat": 35.1154386,
    "lng": 126.8510188,
    "geocode_source": "district"
  },
  {
    "id": 11,
    "sido": "대전",
    "name": "대전오정농수산물도매시장",
    "category": "공영",
    "opened": "198711",
    "corp_count": 3,
    "merchant_count": 0,
    "land_area_sqm": 70854,
    "geocode_query": "대전 대덕구 오정동 농수산물도매시장",
    "lat": 36.3546956,
    "lng": 127.4153096,
    "geocode_source": "district"
  },
  {
    "id": 12,
    "sido": "대전",
    "name": "대전노은농수산물도매시장",
    "category": "공영",
    "opened": "200107",
    "corp_count": 3,
    "merchant_count": 0,
    "land_area_sqm": 112282,
    "geocode_query": "대전 유성구 노은동 농수산물도매시장",
    "lat": 36.369181,
    "lng": 127.3188784,
    "geocode_source": "district"
  },
  {
    "id": 13,
    "sido": "울산",
    "name": "울산농수산물도매시장",
    "category": "공영",
    "opened": "199003",
    "corp_count": 5,
    "merchant_count": 0,
    "land_area_sqm": 41305,
    "geocode_query": "울산 남구 삼산동 농수산물도매시장",
    "lat": 35.54126,
    "lng": 129.34388,
    "geocode_source": "district"
  },
  {
    "id": 14,
    "sido": "경기",
    "name": "수원농수산물도매시장",
    "category": "공영",
    "opened": "199302",
    "corp_count": 5,
    "merchant_count": 0,
    "land_area_sqm": 58960,
    "geocode_query": "수원 권선구 농수산물도매시장",
    "lat": 37.2553054,
    "lng": 127.0311643,
    "geocode_source": "landmark"
  },
  {
    "id": 15,
    "sido": "경기",
    "name": "안양농수산물도매시장",
    "category": "공영",
    "opened": "199709",
    "corp_count": 3,
    "merchant_count": 0,
    "land_area_sqm": 83209,
    "geocode_query": "안양 동안구 호계동 농수산물도매시장",
    "lat": 37.3779842,
    "lng": 126.9543224,
    "geocode_source": "district"
  },
  {
    "id": 16,
    "sido": "경기",
    "name": "안산농수산물도매시장",
    "category": "공영",
    "opened": "199802",
    "corp_count": 3,
    "merchant_count": 0,
    "land_area_sqm": 42499,
    "geocode_query": "안산 단원구 성곡동 농수산물도매시장",
    "lat": 37.31464,
    "lng": 126.74691,
    "geocode_source": "district"
  },
  {
    "id": 17,
    "sido": "경기",
    "name": "구리농수산물도매시장",
    "category": "공영",
    "opened": "199706",
    "corp_count": 5,
    "merchant_count": 0,
    "land_area_sqm": 192838,
    "geocode_query": "구리 인창동 농수산물도매시장",
    "lat": 37.613098,
    "lng": 127.1319711,
    "geocode_source": "district"
  },
  {
    "id": 18,
    "sido": "강원",
    "name": "춘천농수산물도매시장",
    "category": "공영",
    "opened": "199609",
    "corp_count": 2,
    "merchant_count": 0,
    "land_area_sqm": 18265,
    "geocode_query": "춘천 동내면 농수산물도매시장",
    "lat": 37.8480047,
    "lng": 127.7630572,
    "geocode_source": "district"
  },
  {
    "id": 19,
    "sido": "강원",
    "name": "원주농산물도매시장",
    "category": "공영",
    "opened": "200104",
    "corp_count": 2,
    "merchant_count": 0,
    "land_area_sqm": 44800,
    "geocode_query": "원주 우산동 농산물도매시장",
    "lat": 37.3727977,
    "lng": 127.9342003,
    "geocode_source": "district"
  },
  {
    "id": 20,
    "sido": "강원",
    "name": "강릉농산물도매시장",
    "category": "공영",
    "opened": "199911",
    "corp_count": 1,
    "merchant_count": 0,
    "land_area_sqm": 67915,
    "geocode_query": "강릉 농산물도매시장",
    "lat": 37.7541723,
    "lng": 128.9213379,
    "geocode_source": "district"
  },
  {
    "id": 21,
    "sido": "충북",
    "name": "청주농수산물도매시장",
    "category": "공영",
    "opened": "198811",
    "corp_count": 3,
    "merchant_count": 0,
    "land_area_sqm": 44088,
    "geocode_query": "청주 흥덕구 봉명동 농수산물도매시장",
    "lat": 36.6289831,
    "lng": 127.375766,
    "geocode_source": "district"
  },
  {
    "id": 22,
    "sido": "충북",
    "name": "충주농수산물도매시장",
    "category": "공영",
    "opened": "199511",
    "corp_count": 3,
    "merchant_count": 0,
    "land_area_sqm": 45756,
    "geocode_query": "충주 농수산물도매시장",
    "lat": 36.9907334,
    "lng": 127.9259891,
    "geocode_source": "district"
  },
  {
    "id": 23,
    "sido": "충남",
    "name": "천안농수산물도매시장",
    "category": "공영",
    "opened": "199507",
    "corp_count": 3,
    "merchant_count": 0,
    "land_area_sqm": 56395,
    "geocode_query": "천안 서북구 신당동 농수산물도매시장",
    "lat": 36.8783935,
    "lng": 127.1552727,
    "geocode_source": "district"
  },
  {
    "id": 24,
    "sido": "전북",
    "name": "전주농수산물도매시장",
    "category": "공영",
    "opened": "199310",
    "corp_count": 4,
    "merchant_count": 0,
    "land_area_sqm": 59578,
    "geocode_query": "전주 덕진구 팔복동 농수산물도매시장",
    "lat": 35.8294,
    "lng": 127.1342,
    "geocode_source": "district"
  },
  {
    "id": 25,
    "sido": "전북",
    "name": "익산농수산물도매시장",
    "category": "공영",
    "opened": "199801",
    "corp_count": 3,
    "merchant_count": 0,
    "land_area_sqm": 105782,
    "geocode_query": "익산 농수산물도매시장",
    "lat": 35.9479291,
    "lng": 126.9578025,
    "geocode_source": "district"
  },
  {
    "id": 26,
    "sido": "전북",
    "name": "정읍농산물도매시장",
    "category": "공영",
    "opened": "200003",
    "corp_count": 2,
    "merchant_count": 0,
    "land_area_sqm": 70917,
    "geocode_query": "정읍 농산물도매시장",
    "lat": 35.5697678,
    "lng": 126.8559787,
    "geocode_source": "district"
  },
  {
    "id": 27,
    "sido": "전남",
    "name": "순천농산물도매시장",
    "category": "공영",
    "opened": "200104",
    "corp_count": 3,
    "merchant_count": 0,
    "land_area_sqm": 74461,
    "geocode_query": "순천 농산물도매시장",
    "lat": 34.9159489,
    "lng": 127.5390543,
    "geocode_source": "landmark"
  },
  {
    "id": 28,
    "sido": "경북",
    "name": "포항농산물도매시장",
    "category": "공영",
    "opened": "200110",
    "corp_count": 3,
    "merchant_count": 0,
    "land_area_sqm": 84053,
    "geocode_query": "포항 북구 농산물도매시장",
    "lat": 36.0434851,
    "lng": 129.3686129,
    "geocode_source": "district"
  },
  {
    "id": 29,
    "sido": "경북",
    "name": "안동농수산물도매시장",
    "category": "공영",
    "opened": "199704",
    "corp_count": 2,
    "merchant_count": 1,
    "land_area_sqm": 84819,
    "geocode_query": "안동 농수산물도매시장",
    "lat": 36.5634886,
    "lng": 128.7260798,
    "geocode_source": "district"
  },
  {
    "id": 30,
    "sido": "경북",
    "name": "구미농산물도매시장",
    "category": "공영",
    "opened": "200104",
    "corp_count": 2,
    "merchant_count": 0,
    "land_area_sqm": 83049,
    "geocode_query": "구미 농산물도매시장",
    "lat": 36.1562928,
    "lng": 128.3518578,
    "geocode_source": "landmark"
  },
  {
    "id": 31,
    "sido": "경남",
    "name": "창원팔용농산물도매시장",
    "category": "공영",
    "opened": "199510",
    "corp_count": 2,
    "merchant_count": 0,
    "land_area_sqm": 50284,
    "geocode_query": "창원 의창구 팔용동 농산물도매시장",
    "lat": 35.24543,
    "lng": 128.61784,
    "geocode_source": "district"
  },
  {
    "id": 32,
    "sido": "경남",
    "name": "창원내서농산물도매시장",
    "category": "공영",
    "opened": "200212",
    "corp_count": 2,
    "merchant_count": 0,
    "land_area_sqm": 78820,
    "geocode_query": "창원 마산회원구 내서읍 농산물도매시장",
    "lat": 35.2621118,
    "lng": 128.5231997,
    "geocode_source": "district"
  },
  {
    "id": 33,
    "sido": "경남",
    "name": "진주농산물도매시장",
    "category": "공영",
    "opened": "199911",
    "corp_count": 2,
    "merchant_count": 0,
    "land_area_sqm": 60130,
    "geocode_query": "진주 농산물도매시장",
    "lat": 35.2114699,
    "lng": 128.1239842,
    "geocode_source": "landmark"
  },
  {
    "id": 34,
    "sido": "서울",
    "name": "서울노량진수산물도매시장",
    "category": "일반법정",
    "opened": "197106",
    "corp_count": 0,
    "merchant_count": 0,
    "land_area_sqm": 40450,
    "geocode_query": "서울 동작구 노량진수산시장",
    "lat": 37.5147164,
    "lng": 126.9377367,
    "geocode_source": "landmark"
  },
  {
    "id": 35,
    "sido": "서울",
    "name": "서울양재양곡도매시장",
    "category": "일반법정",
    "opened": "198808",
    "corp_count": 0,
    "merchant_count": 0,
    "land_area_sqm": 32095,
    "geocode_query": "서울 서초구 양재동 양곡도매시장",
    "lat": 37.4586226,
    "lng": 127.0369861,
    "geocode_source": "landmark"
  },
  {
    "id": 36,
    "sido": "대구",
    "name": "대구축산도매시장",
    "category": "일반법정",
    "opened": "198104",
    "corp_count": 0,
    "merchant_count": 0,
    "land_area_sqm": 37597,
    "geocode_query": "대구 북구 검단동 축산물도매시장",
    "lat": 35.9138163,
    "lng": 128.6209698,
    "geocode_source": "district"
  },
  {
    "id": 37,
    "sido": "대구",
    "name": "대구한약재도매시장",
    "category": "일반법정",
    "opened": "198207",
    "corp_count": 0,
    "merchant_count": 1,
    "land_area_sqm": 1430,
    "geocode_query": "대구 중구 남성로 약령시",
    "lat": 35.8683,
    "lng": 128.58952,
    "geocode_source": "district"
  },
  {
    "id": 38,
    "sido": "인천",
    "name": "인천가좌축산물도매시장",
    "category": "일반법정",
    "opened": "198206",
    "corp_count": 0,
    "merchant_count": 0,
    "land_area_sqm": 8758,
    "geocode_query": "인천 서구 가좌동 축산물도매시장",
    "lat": 37.4881988,
    "lng": 126.6764228,
    "geocode_source": "district"
  },
  {
    "id": 39,
    "sido": "광주",
    "name": "광주축산물도매시장",
    "category": "일반법정",
    "opened": "198406",
    "corp_count": 0,
    "merchant_count": 0,
    "land_area_sqm": 22735,
    "geocode_query": "광주 북구 각화동 축산물도매시장",
    "lat": 35.1741,
    "lng": 126.9122,
    "geocode_source": "district"
  },
  {
    "id": 40,
    "sido": "전남",
    "name": "목포농산물도매시장",
    "category": "일반법정",
    "opened": "199705",
    "corp_count": 0,
    "merchant_count": 0,
    "land_area_sqm": 14275,
    "geocode_query": "목포 농산물도매시장",
    "lat": 34.7903335,
    "lng": 126.3847547,
    "geocode_source": "district"
  },
  {
    "id": 41,
    "sido": "전남",
    "name": "여수농산물도매시장",
    "category": "일반법정",
    "opened": "201412",
    "corp_count": 0,
    "merchant_count": 0,
    "land_area_sqm": 1560,
    "geocode_query": "여수 농산물도매시장",
    "lat": 34.7546257,
    "lng": 127.659859,
    "geocode_source": "district"
  },
  {
    "id": 42,
    "sido": "경북",
    "name": "포항수산물도매시장",
    "category": "일반법정",
    "opened": "200912",
    "corp_count": 0,
    "merchant_count": 0,
    "land_area_sqm": 14420,
    "geocode_query": "포항 남구 수산물도매시장",
    "lat": 36.0086363,
    "lng": 129.3588062,
    "geocode_source": "district"
  },
  {
    "id": 43,
    "sido": "경북",
    "name": "경주농산물도매시장",
    "category": "일반법정",
    "opened": "196310",
    "corp_count": 0,
    "merchant_count": 0,
    "land_area_sqm": 1173,
    "geocode_query": "경주 농산물도매시장",
    "lat": 35.8556705,
    "lng": 129.2248811,
    "geocode_source": "district"
  },
  {
    "id": 44,
    "sido": "경북",
    "name": "김천농산물도매시장",
    "category": "일반법정",
    "opened": "200605",
    "corp_count": 0,
    "merchant_count": 0,
    "land_area_sqm": 16315,
    "geocode_query": "김천 농산물도매시장",
    "lat": 36.1398035,
    "lng": 128.1139534,
    "geocode_source": "district"
  },
  {
    "id": 45,
    "sido": "경북",
    "name": "영천농산물도매시장",
    "category": "일반법정",
    "opened": "199807",
    "corp_count": 0,
    "merchant_count": 0,
    "land_area_sqm": 7078,
    "geocode_query": "영천 농산물도매시장",
    "lat": 35.98842,
    "lng": 128.942,
    "geocode_source": "district"
  },
  {
    "id": 46,
    "sido": "경북",
    "name": "영천약초도매시장",
    "category": "일반법정",
    "opened": "201510",
    "corp_count": 0,
    "merchant_count": 0,
    "land_area_sqm": 2470,
    "geocode_query": "영천 약초도매시장",
    "lat": 35.98842,
    "lng": 128.942,
    "geocode_source": "district"
  },
  {
    "id": 47,
    "sido": "경기",
    "name": "안양민영축산물도매시장",
    "category": "민영",
    "opened": "199811",
    "corp_count": 0,
    "merchant_count": 0,
    "land_area_sqm": 21566,
    "geocode_query": "안양 축산물도매시장",
    "lat": 37.3938528,
    "lng": 126.9570605,
    "geocode_source": "district"
  },
  {
    "id": 48,
    "sido": "경북",
    "name": "상주민영농산물도매시장",
    "category": "민영",
    "opened": "197208",
    "corp_count": 0,
    "merchant_count": 0,
    "land_area_sqm": 2950,
    "geocode_query": "상주 농산물도매시장",
    "lat": 36.4104478,
    "lng": 128.1590614,
    "geocode_source": "district"
  },
  {
    "id": 49,
    "sido": "경북",
    "name": "영주민영농산물도매시장",
    "category": "민영",
    "opened": "201606",
    "corp_count": 0,
    "merchant_count": 0,
    "land_area_sqm": 33347,
    "geocode_query": "영주 농산물도매시장",
    "lat": 36.805685,
    "lng": 128.624054,
    "geocode_source": "district"
  }
]